gwel/cli.py
gwel/dataset.py
gwel/network.py
gwel/viewer.py
gwel/networks/LociSegmenter.py
gwel/networks/Mask2Former.py
gwel/networks/UNET.py
gwel/networks/YOLOv8.py
gwel/networks/__init__.py
gwel/networks/glm.py
gwel/networks/unet/data_loader.py
gwel/networks/unet/train.py
gwel-0.0.3a0.dist-info/licenses/LICENSE
gwel-0.0.3a0.dist-info/METADATA
gwel-0.0.3a0.dist-info/WHEEL
gwel-0.0.3a0.dist-info/entry_points.txt
gwel-0.0.3a0.dist-info/top_level.txt
gwel-0.0.3a0.dist-info/RECORD
