Metadata-Version: 2.4
Name: gwel
Version: 0.0.3a0
Summary: A computer vision package for handling large image datasets and using neural networks
Author-email: Jack Rich <j.b.c.rich@pgr.reading.ac.uk>
License: MIT
Requires-Python: >=3.8
License-File: LICENSE
Requires-Dist: numpy
Requires-Dist: pandas
Requires-Dist: scipy
Requires-Dist: opencv-python
Requires-Dist: Pillow
Requires-Dist: tqdm
Requires-Dist: pycocotools
Requires-Dist: colorama
Requires-Dist: typer[all]
Dynamic: license-file
